README.rst
setup.cfg
setup.py
rdspg/__init__.py
rdspg/main.py
rdspg/rds.py
rdspg/terraform_cluster.jinja
rdspg/terraform_instance.jinja
rdspg.egg-info/PKG-INFO
rdspg.egg-info/SOURCES.txt
rdspg.egg-info/dependency_links.txt
rdspg.egg-info/entry_points.txt
rdspg.egg-info/requires.txt
rdspg.egg-info/top_level.txt