Metadata-Version: 1.1
Name: rdspg
Version: 0.1.9
Summary: Command-line toolkit to help understand information about your AWS RDS Parameter Groups.
Home-page: https://github.com/cxmcc/rdspg
Author: Xiuming Chen
Author-email: cc@cxm.cc
License: UNKNOWN
Keywords: AWS,RDS,Parameter Groups,Relational Database Service
Platform: UNKNOWN
Classifier: Development Status :: 4 - Beta
Classifier: Environment :: Console
Classifier: Topic :: System :: Clustering
